[
  {
    "manufacturer": "Oppo",
    "market_name": "A59",
    "codename": "A59",
    "model": "OPPO A59"
  },
  {
    "manufacturer": "Oppo",
    "market_name": "A59t",
    "codename": "A59",
    "model": "OPPO A59t"
  },
  {
    "manufacturer": "Oppo",
    "market_name": "OPPO A59",
    "codename": "A59",
    "model": "OPPO A59"
  },
  {
    "manufacturer": "Oppo",
    "market_name": "OPPO A59",
    "codename": "A59",
    "model": "OPPO A59m"
  },
  {
    "manufacturer": "Oppo",
    "market_name": "OPPO A59m",
    "codename": "A59",
    "model": "OPPO A59m"
  },
  {
    "manufacturer": "Oppo",
    "market_name": "OPPO A59t",
    "codename": "A59",
    "model": "OPPO A59t"
  },
  {
    "manufacturer": "Oppo",
    "market_name": "OPPO A59tm",
    "codename": "A59",
    "model": "OPPO A59tm"
  }
]