[
  {
    "manufacturer": "BenQ",
    "market_name": "F5",
    "codename": "F5",
    "model": "BenQ F5"
  },
  {
    "manufacturer": "BenQ",
    "market_name": "F5_06",
    "codename": "F5",
    "model": "F5_06"
  },
  {
    "manufacturer": "BenQ",
    "market_name": "F5_13",
    "codename": "F5",
    "model": "F5_13"
  },
  {
    "manufacturer": "BenQ",
    "market_name": "F5_15",
    "codename": "F5",
    "model": "F5_15"
  },
  {
    "manufacturer": "BenQ",
    "market_name": "F5_16",
    "codename": "F5",
    "model": "F5_16"
  },
  {
    "manufacturer": "BenQ",
    "market_name": "F5_18",
    "codename": "F5",
    "model": "F5_18"
  },
  {
    "manufacturer": "BenQ",
    "market_name": "F5_19",
    "codename": "F5",
    "model": "F5_19"
  },
  {
    "manufacturer": "Galax",
    "market_name": "F5",
    "codename": "F5",
    "model": "F5"
  },
  {
    "manufacturer": "Innjoo",
    "market_name": "F5",
    "codename": "F5",
    "model": "F5"
  }
]