[
  {
    "manufacturer": "Hisense",
    "market_name": "HLTE311T",
    "codename": "HSSDM636QC",
    "model": "HLTE311T"
  },
  {
    "manufacturer": "Hisense",
    "market_name": "HLTE510M",
    "codename": "HSSDM636QC",
    "model": "HLTE510M"
  },
  {
    "manufacturer": "Hisense",
    "market_name": "Hisense H20",
    "codename": "HSSDM636QC",
    "model": "HLTE510T"
  },
  {
    "manufacturer": "Hisense",
    "market_name": "Hisense Infinity H12 Pro",
    "codename": "HSSDM636QC",
    "model": "Hisense Infinity H12 Pro"
  }
]