[
  {
    "manufacturer": "Huawei",
    "market_name": "HUAWEI Y5 2019",
    "codename": "HWAMN-M",
    "model": "AMN-LX1"
  },
  {
    "manufacturer": "Huawei",
    "market_name": "HUAWEI Y5 2019",
    "codename": "HWAMN-M",
    "model": "AMN-LX2"
  },
  {
    "manufacturer": "Huawei",
    "market_name": "HUAWEI Y5 2019",
    "codename": "HWAMN-M",
    "model": "AMN-LX3"
  },
  {
    "manufacturer": "Huawei",
    "market_name": "HUAWEI Y5 2019",
    "codename": "HWAMN-M",
    "model": "AMN-LX9"
  }
]