[
  {
    "manufacturer": "Acer",
    "market_name": "I110",
    "codename": "I1",
    "model": "I110"
  },
  {
    "manufacturer": "Acer",
    "market_name": "Liquid C1",
    "codename": "I1",
    "model": "I110"
  },
  {
    "manufacturer": "Coolpad",
    "market_name": "i1",
    "codename": "i1",
    "model": "ivvi i1"
  },
  {
    "manufacturer": "Ghia",
    "market_name": "I1",
    "codename": "I1",
    "model": "I1"
  },
  {
    "manufacturer": "iVOOMi",
    "market_name": "i1",
    "codename": "i1",
    "model": "i1"
  }
]