[
  {
    "manufacturer": "Vivo",
    "market_name": "vivo X5MaxV",
    "codename": "msm8916_32",
    "model": "vivo X5MaxV"
  },
  {
    "manufacturer": "ZTE",
    "market_name": "Avea inTouch 4",
    "codename": "msm8916_32",
    "model": "Avea inTouch 4"
  },
  {
    "manufacturer": "ZTE",
    "market_name": "Avea inTouch 4",
    "codename": "msm8916_32",
    "model": "ZTE Blade V220"
  },
  {
    "manufacturer": "ZTE",
    "market_name": "Preo Teknosa P1",
    "codename": "msm8916_32",
    "model": "Preo Teknosa P1"
  },
  {
    "manufacturer": "ZTE",
    "market_name": "TURKCELL T60",
    "codename": "msm8916_32",
    "model": "TURKCELL T60"
  },
  {
    "manufacturer": "ZTE",
    "market_name": "Ultym 5.2",
    "codename": "msm8916_32",
    "model": "Ultym 5.2"
  },
  {
    "manufacturer": "ZTE",
    "market_name": "Vodafone Smart ultra 6",
    "codename": "msm8916_32",
    "model": "Vodafone Smart ultra 6"
  },
  {
    "manufacturer": "ZTE",
    "market_name": "ZTE Blade Apex3",
    "codename": "msm8916_32",
    "model": "ZTE Blade Apex3"
  },
  {
    "manufacturer": "ZTE",
    "market_name": "ZTE Blade V2",
    "codename": "msm8916_32",
    "model": "ZTE Blade V2"
  },
  {
    "manufacturer": "ZTE",
    "market_name": "ZTE Blade V220",
    "codename": "msm8916_32",
    "model": "ZTE Blade V220"
  }
]