[
  {
    "manufacturer": "TCT (Alcatel)",
    "market_name": "A3 XL",
    "codename": "PIXI5-6_4G",
    "model": "9008A"
  },
  {
    "manufacturer": "TCT (Alcatel)",
    "market_name": "A3 XL",
    "codename": "PIXI5-6_4G",
    "model": "9008D"
  },
  {
    "manufacturer": "TCT (Alcatel)",
    "market_name": "A3 XL",
    "codename": "PIXI5-6_4G",
    "model": "9008I"
  },
  {
    "manufacturer": "TCT (Alcatel)",
    "market_name": "A3 XL",
    "codename": "PIXI5-6_4G",
    "model": "9008J"
  },
  {
    "manufacturer": "TCT (Alcatel)",
    "market_name": "A3 XL",
    "codename": "PIXI5-6_4G",
    "model": "9008N"
  },
  {
    "manufacturer": "TCT (Alcatel)",
    "market_name": "A3 XL",
    "codename": "PIXI5-6_4G",
    "model": "9008T"
  },
  {
    "manufacturer": "TCT (Alcatel)",
    "market_name": "A3 XL",
    "codename": "PIXI5-6_4G",
    "model": "9008U"
  },
  {
    "manufacturer": "TCT (Alcatel)",
    "market_name": "A3 XL",
    "codename": "PIXI5-6_4G",
    "model": "9008X"
  },
  {
    "manufacturer": "TCT (Alcatel)",
    "market_name": "A3 XL",
    "codename": "PIXI5-6_4G",
    "model": "9108A"
  },
  {
    "manufacturer": "TCT (Alcatel)",
    "market_name": "A3 XL",
    "codename": "PIXI5-6_4G",
    "model": "TCLGalaG60(9108A)"
  }
]