[
  {
    "manufacturer": "Lenovo",
    "market_name": "Thinkpad 11e Chromebook (4th Gen)/Lenovo Thinkpad Yoga 11e Chromebook (4th Gen)",
    "codename": "pyro_cheets",
    "model": "Lenovo ThinkPad 11e 4th Gen Chromebook"
  },
  {
    "manufacturer": "Lenovo",
    "market_name": "Thinkpad 11e Chromebook (4th Gen)/Lenovo Thinkpad Yoga 11e Chromebook (4th Gen)",
    "codename": "pyro_cheets",
    "model": "Lenovo Thinkpad 11e Chromebook (4th Gen)/Lenovo Thinkpad Yoga 11e Chromebook (4th Gen)"
  }
]