[
  {
    "manufacturer": "AV",
    "market_name": "AV10",
    "codename": "RCT6203W46",
    "model": "AV10"
  },
  {
    "manufacturer": "Dopo",
    "market_name": "DPM1081",
    "codename": "RCT6203W46",
    "model": "DPM1081"
  },
  {
    "manufacturer": "Hipstreet",
    "market_name": "HS-10DTB12A",
    "codename": "RCT6203W46",
    "model": "HS_10DTB12A"
  },
  {
    "manufacturer": "Nobis",
    "market_name": "NB1022",
    "codename": "RCT6203W46",
    "model": "NB1022"
  },
  {
    "manufacturer": "Polaroid",
    "market_name": "MID4X10",
    "codename": "RCT6203W46",
    "model": "MID4X10"
  },
  {
    "manufacturer": "Polaroid",
    "market_name": "PTAB1051-PTAB1055",
    "codename": "RCT6203W46",
    "model": "PTAB1051_PTAB1055"
  },
  {
    "manufacturer": "RCA",
    "market_name": "RCT6203W46",
    "codename": "RCT6203W46",
    "model": "RCT6203W46"
  }
]