[
  {
    "manufacturer": "Blackview",
    "market_name": "S8",
    "codename": "S8",
    "model": "S8"
  },
  {
    "manufacturer": "Blackview",
    "market_name": "S8_RU",
    "codename": "S8",
    "model": "S8"
  },
  {
    "manufacturer": "Elephone",
    "market_name": "Elephone S8",
    "codename": "S8",
    "model": "S8"
  },
  {
    "manufacturer": "HOMTOM",
    "market_name": "S8",
    "codename": "S8",
    "model": "S8"
  },
  {
    "manufacturer": "Leagoo",
    "market_name": "S8",
    "codename": "S8",
    "model": "S8"
  },
  {
    "manufacturer": "OTOT",
    "market_name": "S8",
    "codename": "S8",
    "model": "S8"
  },
  {
    "manufacturer": "Tech 4u",
    "market_name": "Tech4U S8",
    "codename": "S8",
    "model": "S8"
  },
  {
    "manufacturer": "Ulefone",
    "market_name": "S8",
    "codename": "S8",
    "model": "Ulefone S8"
  },
  {
    "manufacturer": "Ulefone",
    "market_name": "S8_",
    "codename": "S8",
    "model": "Ulefone S8"
  }
]