[
  {
    "manufacturer": "LGE",
    "market_name": "LG Optimus 3D",
    "codename": "cosmopolitan",
    "model": "LG-P920"
  },
  {
    "manufacturer": "LGE",
    "market_name": "LG Optimus 3D",
    "codename": "cosmopolitan",
    "model": "LG-P925g"
  },
  {
    "manufacturer": "LGE",
    "market_name": "LG Optimus 3D",
    "codename": "cosmopolitan",
    "model": "LG-SU760"
  },
  {
    "manufacturer": "LGE",
    "market_name": "LG Thrill 4G",
    "codename": "cosmopolitan",
    "model": "LG-P925"
  }
]