[
  {
    "manufacturer": "Huawei",
    "market_name": "Mate S",
    "codename": "HWCRR",
    "model": "HUAWEI CRR-CL00"
  },
  {
    "manufacturer": "Huawei",
    "market_name": "Mate S",
    "codename": "HWCRR",
    "model": "HUAWEI CRR-CL20"
  },
  {
    "manufacturer": "Huawei",
    "market_name": "Mate S",
    "codename": "HWCRR",
    "model": "HUAWEI CRR-L09"
  },
  {
    "manufacturer": "Huawei",
    "market_name": "Mate S",
    "codename": "HWCRR",
    "model": "HUAWEI CRR-TL00"
  },
  {
    "manufacturer": "Huawei",
    "market_name": "Mate S",
    "codename": "HWCRR",
    "model": "HUAWEI CRR-UL00"
  },
  {
    "manufacturer": "Huawei",
    "market_name": "Mate S",
    "codename": "HWCRR",
    "model": "HUAWEI CRR-UL20"
  }
]