[
  {
    "manufacturer": "TCT (Alcatel)",
    "market_name": "ALCATEL ONE TOUCH 4037N",
    "codename": "SOUL4NA",
    "model": "ALCATEL ONE TOUCH 4037N"
  },
  {
    "manufacturer": "TCT (Alcatel)",
    "market_name": "ALCATEL ONE TOUCH 4037N",
    "codename": "SOUL4NA",
    "model": "ALCATEL ONE TOUCH 4037T"
  },
  {
    "manufacturer": "TCT (Alcatel)",
    "market_name": "ALCATEL ONETOUCH 4037R",
    "codename": "SOUL4NA",
    "model": "ALCATEL ONE TOUCH 4037R"
  },
  {
    "manufacturer": "TCT (Alcatel)",
    "market_name": "ALCATEL ONETOUCH 4037R",
    "codename": "SOUL4NA",
    "model": "ALCATEL ONETOUCH 4037R"
  },
  {
    "manufacturer": "TCT (Alcatel)",
    "market_name": "ALCATEL ONETOUCH POP D3",
    "codename": "SOUL4NA",
    "model": "ALCATEL ONETOUCH POP D3"
  }
]