[
  {
    "manufacturer": "Motorola",
    "market_name": "Moto E with 4G LTE (2nd Gen)",
    "codename": "surnia_cdma",
    "model": "MotoE2"
  },
  {
    "manufacturer": "Motorola",
    "market_name": "Moto E with 4G LTE (2nd Gen)",
    "codename": "surnia_cdma",
    "model": "MotoE2(4G-LTE)"
  },
  {
    "manufacturer": "Motorola",
    "market_name": "Moto E with 4G LTE (2nd Gen)",
    "codename": "surnia_cdma",
    "model": "XT1526"
  },
  {
    "manufacturer": "Motorola",
    "market_name": "Moto E with 4G LTE (2nd Gen)",
    "codename": "surnia_cdma",
    "model": "XT1528"
  },
  {
    "manufacturer": "Motorola",
    "market_name": "Moto E with 4G LTE (2nd Gen)",
    "codename": "surnia_cdma",
    "model": "XT1528O"
  }
]