{
  "manufacturer": "BQru",
  "devices": [
    {
      "manufacturer": "",
      "market_name": "5060",
      "codename": "BQru-5060",
      "model": "BQru-5060"
    },
    {
      "manufacturer": "",
      "market_name": "BQ 5503 NICE 2",
      "codename": "BQru_5503",
      "model": "BQru-5503"
    },
    {
      "manufacturer": "",
      "market_name": "BQ-4028UP!",
      "codename": "BQru-4028",
      "model": "BQru-4028"
    },
    {
      "manufacturer": "",
      "market_name": "BQ-4072 Strike Mini",
      "codename": "BQru_4072",
      "model": "BQru-4072"
    },
    {
      "manufacturer": "",
      "market_name": "BQ-4500L",
      "codename": "BQru-4500",
      "model": "BQru-4500"
    },
    {
      "manufacturer": "",
      "market_name": "BQ-5000L",
      "codename": "BQru-5000",
      "model": "BQru-5000"
    },
    {
      "manufacturer": "",
      "market_name": "BQ-5033 Shark",
      "codename": "BQru_5033",
      "model": "BQru-5033"
    },
    {
      "manufacturer": "",
      "market_name": "BQ-5035 Velvet",
      "codename": "BQru-5035",
      "model": "BQru-5035"
    },
    {
      "manufacturer": "",
      "market_name": "BQ-5044 Strike LTE",
      "codename": "BQru-5044",
      "model": "BQru-5044"
    },
    {
      "manufacturer": "",
      "market_name": "BQ-5057 Strike 2",
      "codename": "BQru_5057",
      "model": "BQru-5057"
    },
    {
      "manufacturer": "",
      "market_name": "BQ-5058 Strike Power Easy",
      "codename": "BQru-5058",
      "model": "BQru_BQru-5058"
    },
    {
      "manufacturer": "",
      "market_name": "BQ-5059 Strike Power",
      "codename": "BQru_5059",
      "model": "BQru-5059"
    },
    {
      "manufacturer": "",
      "market_name": "BQ-5201",
      "codename": "BQru-5201",
      "model": "BQru-5201"
    },
    {
      "manufacturer": "",
      "market_name": "BQ-5202",
      "codename": "BQru-5202",
      "model": "BQru-5202"
    },
    {
      "manufacturer": "",
      "market_name": "BQ-5203 Shark",
      "codename": "BQru-5203",
      "model": "BQru-5203"
    },
    {
      "manufacturer": "",
      "market_name": "BQ-5204 Strike Selfie",
      "codename": "BQru-5204",
      "model": "BQru-5204"
    },
    {
      "manufacturer": "",
      "market_name": "BQ-5504\\xc2\\xa0Strike\\xc2\\xa0Selfie\\xc2\\xa0Max",
      "codename": "BQru_5504",
      "model": "BQru-5504"
    },
    {
      "manufacturer": "",
      "market_name": "BQ-5510 Strike Power Max 4G",
      "codename": "BQru_5510",
      "model": "BQru-5510"
    },
    {
      "manufacturer": "",
      "market_name": "BQ-5521 STRIKE POWER MAX",
      "codename": "BQru-5521",
      "model": "BQru-5521"
    },
    {
      "manufacturer": "",
      "market_name": "BQ-5590 Spring",
      "codename": "BQru_5590",
      "model": "BQru_5590"
    },
    {
      "manufacturer": "",
      "market_name": "BQ-7081G",
      "codename": "BQru-7081",
      "model": "BQru-7081"
    },
    {
      "manufacturer": "",
      "market_name": "BQru-1081G",
      "codename": "BQru-1081G",
      "model": "BQru-1081G"
    },
    {
      "manufacturer": "",
      "market_name": "BQru-4526",
      "codename": "BQru-4526",
      "model": "BQru-4526"
    },
    {
      "manufacturer": "",
      "market_name": "BQru-5022",
      "codename": "BQru",
      "model": "BQru-5022"
    },
    {
      "manufacturer": "",
      "market_name": "BQru-7082",
      "codename": "BQru-7082",
      "model": "BQru-7082"
    },
    {
      "manufacturer": "",
      "market_name": "BQru-7083",
      "codename": "BQru-7083",
      "model": "BQru-7083"
    },
    {
      "manufacturer": "",
      "market_name": "Bqru-5037",
      "codename": "BQru-5037",
      "model": "BQru-5037"
    },
    {
      "manufacturer": "",
      "market_name": "CRYSTAL",
      "codename": "BQru-5054",
      "model": "BQru-5054"
    },
    {
      "manufacturer": "",
      "market_name": "FOX  POWER",
      "codename": "BQru-4583",
      "model": "BQru-4583"
    },
    {
      "manufacturer": "",
      "market_name": "FOX POWER",
      "codename": "BQru-4583",
      "model": "BQru-4583"
    }
  ]
}