{
  "manufacturer": "Denver Electronics",
  "devices": [
    {
      "manufacturer": "",
      "market_name": "SDQ-55034L",
      "codename": "SDQ-55034L",
      "model": "SDQ-55034L"
    },
    {
      "manufacturer": "",
      "market_name": "SDQ_52004L",
      "codename": "SDQ_52004L",
      "model": "SDQ_52004L"
    },
    {
      "manufacturer": "",
      "market_name": "TAQ-10",
      "codename": "TAQ10",
      "model": "TAQ-10"
    },
    {
      "manufacturer": "",
      "market_name": "TAQ-102",
      "codename": "TAQ102",
      "model": "TAQ-102"
    }
  ]
}