{
  "manufacturer": "FIREFLY MOBILE",
  "devices": [
    {
      "manufacturer": "",
      "market_name": "AURII_AMUSE_3G",
      "codename": "AURII_AMUSE_3G",
      "model": "AURII_AMUSE_3G"
    },
    {
      "manufacturer": "",
      "market_name": "FIREFLY MOBILE",
      "codename": "AURII_XCITE",
      "model": "AURII_XCITE"
    },
    {
      "manufacturer": "",
      "market_name": "INTENSE_XT",
      "codename": "INTENSE_XT",
      "model": "INTENSE_XT"
    },
    {
      "manufacturer": "",
      "market_name": "Inspire_4G",
      "codename": "INSPIRE_4G",
      "model": "INSPIRE_4G"
    },
    {
      "manufacturer": "",
      "market_name": "SECRET_XR",
      "codename": "SECRET_XR",
      "model": "SECRET_XR"
    },
    {
      "manufacturer": "",
      "market_name": "VIVID_PRO",
      "codename": "VIVID_PRO",
      "model": "VIVID_PRO"
    }
  ]
}