{
  "manufacturer": "Jivi",
  "devices": [
    {
      "manufacturer": "",
      "market_name": "Energy E12",
      "codename": "Energy_E12",
      "model": "Energy E12"
    },
    {
      "manufacturer": "",
      "market_name": "Prime P30",
      "codename": "Prime_P30",
      "model": "Prime P30"
    },
    {
      "manufacturer": "",
      "market_name": "Prime P444",
      "codename": "Prime_P444",
      "model": "Prime P444"
    },
    {
      "manufacturer": "",
      "market_name": "Prime P4442",
      "codename": "Prime_P4442",
      "model": "Prime P4442"
    }
  ]
}