{
  "manufacturer": "Mito",
  "devices": [
    {
      "manufacturer": "",
      "market_name": "A10",
      "codename": "A10_sprout",
      "model": "MITO A10"
    },
    {
      "manufacturer": "",
      "market_name": "A10",
      "codename": "A10_sprout",
      "model": "MITO_A10"
    },
    {
      "manufacturer": "",
      "market_name": "A62",
      "codename": "A62",
      "model": "A62"
    },
    {
      "manufacturer": "",
      "market_name": "A67",
      "codename": "A67",
      "model": "Mito A67"
    },
    {
      "manufacturer": "",
      "market_name": "A880",
      "codename": "A880",
      "model": "MITO A880"
    },
    {
      "manufacturer": "",
      "market_name": "MITO A17",
      "codename": "MITO_A17",
      "model": "MITO A17"
    },
    {
      "manufacturer": "",
      "market_name": "MITO A21",
      "codename": "A21",
      "model": "MITO A21"
    },
    {
      "manufacturer": "",
      "market_name": "MITO A39",
      "codename": "A39",
      "model": "mito A39"
    },
    {
      "manufacturer": "",
      "market_name": "MITO T8",
      "codename": "MITO_T8",
      "model": "MITO T8"
    },
    {
      "manufacturer": "",
      "market_name": "MITO T85",
      "codename": "T85",
      "model": "MITO T85"
    },
    {
      "manufacturer": "",
      "market_name": "MITO_A19_1GB",
      "codename": "MITO_A19_1GB",
      "model": "MITO_A19_1GB"
    },
    {
      "manufacturer": "",
      "market_name": "MITO_A19_2GB",
      "codename": "MITO_A19_2GB",
      "model": "MITO_A19_2GB"
    },
    {
      "manufacturer": "",
      "market_name": "Mito_A36_W1",
      "codename": "MITO_A36_W1",
      "model": "MITO_A36_W1"
    },
    {
      "manufacturer": "",
      "market_name": "Mito_A37_Z1",
      "codename": "MITO_A37_Z1",
      "model": "MITO_A37_Z1"
    },
    {
      "manufacturer": "",
      "market_name": "Mito_A37_Z1",
      "codename": "MITO_A37_Z1plus",
      "model": "MITO_A37_Z1plus"
    },
    {
      "manufacturer": "",
      "market_name": "T5091A",
      "codename": "MITO_A16",
      "model": "MITO A16"
    }
  ]
}