{
  "manufacturer": "MyPhone (PL)",
  "devices": [
    {
      "manufacturer": "",
      "market_name": "C-Smart pix",
      "codename": "C-Smart_pix_JMP",
      "model": "C-Smart_pix"
    },
    {
      "manufacturer": "",
      "market_name": "Cube LTE",
      "codename": "CUBE_LTE_PLAY",
      "model": "CUBE_LTE"
    },
    {
      "manufacturer": "",
      "market_name": "Fun_LTE",
      "codename": "Fun_LTE",
      "model": "myPhone Fun LTE"
    },
    {
      "manufacturer": "",
      "market_name": "Hammer AXE PRO",
      "codename": "Hammer_AXE_Pro_OPM",
      "model": "Hammer AXE Pro"
    },
    {
      "manufacturer": "",
      "market_name": "Hammer Blade 2 PRO",
      "codename": "Hammer_Blade2_PRO",
      "model": "Hammer_Blade2_PRO"
    },
    {
      "manufacturer": "",
      "market_name": "Hammer Titan 2",
      "codename": "Hammer_Titan_2",
      "model": "Hammer Titan 2"
    },
    {
      "manufacturer": "",
      "market_name": "Hammer_Active",
      "codename": "HammerActive",
      "model": "Hammer Active"
    },
    {
      "manufacturer": "",
      "market_name": "Hammer_Energy_3G",
      "codename": "Hammer_Energy_3G",
      "model": "Hammer Energy 3G"
    },
    {
      "manufacturer": "",
      "market_name": "Hammer_Iron_2",
      "codename": "Hammer_Iron_2",
      "model": "Hammer Iron 2"
    },
    {
      "manufacturer": "",
      "market_name": "Hykker MyTab10",
      "codename": "Hykker_MyTab10",
      "model": "Hykker_MyTab10"
    },
    {
      "manufacturer": "",
      "market_name": "MyPhone Go!",
      "codename": "myPhone_Go",
      "model": "myPhone Go"
    },
    {
      "manufacturer": "",
      "market_name": "myPhone",
      "codename": "Q_Smart_BE",
      "model": "Q_Smart_BE"
    },
    {
      "manufacturer": "",
      "market_name": "myPhone C-Smart Glam",
      "codename": "C-Smart_Glam_JMP",
      "model": "C-Smart_Glam"
    },
    {
      "manufacturer": "",
      "market_name": "myPhone C-Smart IIIS",
      "codename": "C_Smart_IIIS",
      "model": "C-Smart IIIS"
    },
    {
      "manufacturer": "",
      "market_name": "myPhone City",
      "codename": "myPhone_City",
      "model": "City"
    },
    {
      "manufacturer": "",
      "market_name": "myPhone Fun 5",
      "codename": "FUN5_OPM",
      "model": "FUN5"
    },
    {
      "manufacturer": "",
      "market_name": "myPhone HAMMER ENERGY",
      "codename": "HAMMER_ENERGY_PLAY",
      "model": "HAMMER_ENERGY"
    },
    {
      "manufacturer": "",
      "market_name": "myPhone Hammer Energy",
      "codename": "Hammer_Energy",
      "model": "Hammer Energy"
    },
    {
      "manufacturer": "",
      "market_name": "myPhone Luna II",
      "codename": "LUNA_II_OPM",
      "model": "LUNA_II"
    },
    {
      "manufacturer": "",
      "market_name": "myPhone MAGNUS",
      "codename": "MAGNUS_JMP",
      "model": "MAGNUS"
    },
    {
      "manufacturer": "",
      "market_name": "myPhone PRIME PLUS",
      "codename": "Prime_Plus_OPM",
      "model": "Prime_Plus"
    },
    {
      "manufacturer": "",
      "market_name": "myPhone Pocket",
      "codename": "Pocket_OPM",
      "model": "Pocket"
    },
    {
      "manufacturer": "",
      "market_name": "myPhone Prime 3",
      "codename": "myPhone_Prime_3",
      "model": "myPhone_Prime_3"
    },
    {
      "manufacturer": "",
      "market_name": "myPhone Q-Smart Elite",
      "codename": "Q-Smart_Elite_JMP",
      "model": "Q-Smart_Elite"
    },
    {
      "manufacturer": "",
      "market_name": "myPhone Q-Smart Plus",
      "codename": "Q-Smart_Plus",
      "model": "Q-Smart_Plus"
    },
    {
      "manufacturer": "",
      "market_name": "myPhone_C-Smart _4",
      "codename": "myPhone_C-Smart_4",
      "model": "myPhone_C-Smart_4"
    },
    {
      "manufacturer": "",
      "market_name": "myPhone_Fun5",
      "codename": "myPhone_Fun5",
      "model": "Fun5"
    },
    {
      "manufacturer": "",
      "market_name": "myPhone_Power",
      "codename": "myPhone_Power",
      "model": "Power"
    },
    {
      "manufacturer": "",
      "market_name": "myPhone_Prime_2",
      "codename": "myPhone_Prime_2",
      "model": "Prime 2"
    }
  ]
}