{
  "manufacturer": "Remdun",
  "devices": [
    {
      "manufacturer": "",
      "market_name": "RD-52",
      "codename": "RD52",
      "model": "RD52"
    },
    {
      "manufacturer": "",
      "market_name": "RD52E",
      "codename": "RD52E",
      "model": "RD52E"
    },
    {
      "manufacturer": "",
      "market_name": "RD62E",
      "codename": "RD62E",
      "model": "RD62E"
    },
    {
      "manufacturer": "",
      "market_name": "RD86",
      "codename": "RD86",
      "model": "RD86"
    },
    {
      "manufacturer": "",
      "market_name": "RD86E",
      "codename": "RD86E",
      "model": "RD86E"
    }
  ]
}