{
  "manufacturer": "Umidigi",
  "devices": [
    {
      "manufacturer": "",
      "market_name": "A3",
      "codename": "A3",
      "model": "A3"
    },
    {
      "manufacturer": "",
      "market_name": "A3_Pro",
      "codename": "A3_Pro",
      "model": "A3_Pro"
    },
    {
      "manufacturer": "",
      "market_name": "A5 Pro",
      "codename": "A5_Pro",
      "model": "A5_Pro"
    },
    {
      "manufacturer": "",
      "market_name": "F1",
      "codename": "F1",
      "model": "F1"
    },
    {
      "manufacturer": "",
      "market_name": "F1_EEA",
      "codename": "F1",
      "model": "F1"
    },
    {
      "manufacturer": "",
      "market_name": "One",
      "codename": "One",
      "model": "One"
    },
    {
      "manufacturer": "",
      "market_name": "One Max",
      "codename": "One_Max",
      "model": "One Max"
    },
    {
      "manufacturer": "",
      "market_name": "One Max E",
      "codename": "One_Max",
      "model": "One Max"
    },
    {
      "manufacturer": "",
      "market_name": "One Max RU",
      "codename": "One_Max",
      "model": "One Max"
    },
    {
      "manufacturer": "",
      "market_name": "One Pro",
      "codename": "One_Pro",
      "model": "One Pro"
    },
    {
      "manufacturer": "",
      "market_name": "Power",
      "codename": "Power",
      "model": "Power"
    },
    {
      "manufacturer": "",
      "market_name": "S2PRO",
      "codename": "S2_PRO",
      "model": "S2_PRO"
    },
    {
      "manufacturer": "",
      "market_name": "S3_Pro",
      "codename": "S3_Pro",
      "model": "S3_Pro"
    },
    {
      "manufacturer": "",
      "market_name": "UMIDIGI X",
      "codename": "UMIDIGI_X",
      "model": "UMIDIGI X"
    },
    {
      "manufacturer": "",
      "market_name": "Z2",
      "codename": "Z2",
      "model": "Z2"
    },
    {
      "manufacturer": "",
      "market_name": "Z2 Pro",
      "codename": "Z2_PRO",
      "model": "Z2_PRO"
    }
  ]
}